hermes/__init__.py
hermes/moxy/__init__.py
hermes/moxy/producer.py
hermes/moxy/stream.py
pysio_hermes_moxy-0.0.1.dist-info/licenses/LICENSE
pysio_hermes_moxy-0.0.1.dist-info/METADATA
pysio_hermes_moxy-0.0.1.dist-info/WHEEL
pysio_hermes_moxy-0.0.1.dist-info/top_level.txt
pysio_hermes_moxy-0.0.1.dist-info/RECORD
