Metadata-Version: 2.4
Name: pysio-hermes-moxy
Version: 0.0.1
Summary: A Moxy oxygenation support module for HERMES
Author: e-Media Research Lab @ KU Leuven
Author-email: Maxim Yudayev <maxim.yudayev@gmail.com>
License-Expression: MIT
Project-URL: Homepage, https://maximyudayev.github.io/hermes
Project-URL: Documentation, https://maximyudayev.github.io/hermes
Project-URL: Repository, https://github.com/maximyudayev/hermes-moxy.git
Project-URL: Issues, https://github.com/maximyudayev/hermes/issues
Project-URL: Changelog, https://github.com/maximyudayev/hermes-moxy/blob/main/CHANGELOG.md
Keywords: embedded ai,wearables,sensors,oxygenation,moxy,streaming,realtime processing,physiology
Classifier: Programming Language :: Python :: 3
Classifier: Operating System :: OS Independent
Classifier: Development Status :: 4 - Beta
Classifier: Intended Audience :: Healthcare Industry
Classifier: Intended Audience :: Education
Classifier: Intended Audience :: Developers
Classifier: Intended Audience :: Science/Research
Classifier: Topic :: Scientific/Engineering
Classifier: Topic :: Scientific/Engineering :: Artificial Intelligence
Classifier: Topic :: Scientific/Engineering :: Medical Science Apps.
Classifier: Topic :: System :: Distributed Computing
Requires-Python: >=3.7
License-File: LICENSE
Requires-Dist: pysio-hermes
Requires-Dist: openant
Dynamic: license-file
